alidade-client/__init__.py
alidade-client/client.py
alidade-client/connection.py
alidade_client/__init__.py
alidade_client/client.py
alidade_client/connection.py
periplus_client/__init__.py
periplus_client/client.py
periplus_client/connection.py
periplus_client/error.py
periplus_client-0.1.0a1.dist-info/LICENSE
periplus_client-0.1.0a1.dist-info/METADATA
periplus_client-0.1.0a1.dist-info/WHEEL
periplus_client-0.1.0a1.dist-info/top_level.txt
periplus_client-0.1.0a1.dist-info/RECORD
